dashtools/__init__.py
dashtools/version.py
dashtools/cli/__init__.py
dashtools/cli/cli.py
dashtools/cli/update.py
dashtools/dashboard/__init__.py
dashtools/dashboard/alerts.py
dashtools/dashboard/dashboard.py
dashtools/dashboard/tree.py
dashtools/dashboard/assets/advanced-banner.svg
dashtools/dashboard/assets/code.css
dashtools/dashboard/assets/confetti_effect.js
dashtools/dashboard/assets/dash_leaflet_cached.min.js
dashtools/dashboard/assets/dashtools_logo_w_blk_bkg.png
dashtools/dashboard/assets/favicon.ico
dashtools/dashboard/assets/four-cute-cats.jpeg
dashtools/dashboard/assets/golden-retriever-dog.jpeg
dashtools/dashboard/assets/logo.css
dashtools/dashboard/assets/logo_bk.png
dashtools/dashboard/assets/logo_bk_small.png
dashtools/dashboard/assets/logo_w.png
dashtools/dashboard/assets/logo_w_small.png
dashtools/dashboard/callbacks/__init__.py
dashtools/dashboard/callbacks/createPage_callbacks.py
dashtools/dashboard/callbacks/deployPage_callbacks.py
dashtools/dashboard/callbacks/router.py
dashtools/dashboard/components/__init__.py
dashtools/dashboard/components/sidebar.py
dashtools/dashboard/pages/__init__.py
dashtools/dashboard/pages/createPage.py
dashtools/dashboard/pages/deployPage.py
dashtools/dashboard/pages/errorPage.py
dashtools/dashboard/pages/explorePage.py
dashtools/dashboard/pages/helpPage.py
dashtools/data/__init__.py
dashtools/data/configUtils.py
dashtools/data/nounlist.csv
dashtools/data/randomWords.py
dashtools/deploy/__init__.py
dashtools/deploy/deployHeroku.py
dashtools/deploy/fileUtils.py
dashtools/deploy/gitUtils.py
dashtools/deploy/herokuUtils.py
dashtools/docker/__init__.py
dashtools/docker/dockerUtils.py
dashtools/runtime/__init__.py
dashtools/runtime/runtimeUtils.py
dashtools/templating/Templates.py
dashtools/templating/__init__.py
dashtools/templating/buildApp.py
dashtools/templating/buildAppUtils.py
dashtools/templating/createTemplate.py
dashtools/templating/templates/advanced/Procfile.template
dash_tools-1.12.0.dist-info/LICENSE
dash_tools-1.12.0.dist-info/METADATA
dash_tools-1.12.0.dist-info/WHEEL
dash_tools-1.12.0.dist-info/entry_points.txt
dash_tools-1.12.0.dist-info/top_level.txt
dash_tools-1.12.0.dist-info/RECORD
