Metadata-Version: 2.1
Name: dash-tools
Version: 1.12.0
Summary: Plotly Dash Templating and Deployment Tools
Home-page: https://github.com/andrew-hossack/dash-tools
Author: Andrew Hossack
Author-email: andrew_hossack@outlook.com
Classifier: Programming Language :: Python :: 3
Classifier: License :: OSI Approved :: MIT License
Classifier: Operating System :: OS Independent
Requires-Python: >=3.6
License-File: LICENSE
Requires-Dist: dash>=2.5.1
Requires-Dist: dash-bootstrap-components
Requires-Dist: Flask
Requires-Dist: gunicorn
Requires-Dist: packaging==21.3
Requires-Dist: pipreqs==0.4.12
Requires-Dist: pre-commit==2.16.0
Requires-Dist: pytest==6.2.5
Requires-Dist: pandas
Requires-Dist: yolk3k==0.9
Requires-Dist: termcolor==1.1.0
Requires-Dist: visdcc==0.0.50
Requires-Dist: dash-mantine-components==0.12.0
Requires-Dist: dash-iconify==0.1.2
Requires-Dist: ruamel.yaml==0.17.21
Requires-Dist: setuptools>=65.5.1
